[
    {
        "date": "03/25/2026 00:49:41",
        "failed": 30,
        "passed": 1772,
        "skipped": 0,
        "total_ops": 0,
        "versions": [
            {
                "name": "onnx",
                "version": "1.20.1"
            }
        ]
    },
    {
        "date": "03/27/2026 00:52:44",
        "failed": 30,
        "passed": 1772,
        "skipped": 0,
        "total_ops": 199,
        "versions": [
            {
                "name": "onnx",
                "version": "1.20.1"
            }
        ]
    },
    {
        "date": "03/29/2026 00:55:54",
        "failed": 30,
        "passed": 1797,
        "skipped": 0,
        "total_ops": 201,
        "versions": [
            {
                "name": "onnx",
                "version": "1.21.0"
            }
        ]
    },
    {
        "date": "03/30/2026 00:55:17",
        "failed": 31,
        "passed": 1796,
        "skipped": 0,
        "total_ops": 201,
        "versions": [
            {
                "name": "onnx",
                "version": "1.21.0"
            }
        ]
    },
    {
        "date": "03/31/2026 00:52:38",
        "failed": 30,
        "passed": 1797,
        "skipped": 0,
        "total_ops": 201,
        "versions": [
            {
                "name": "onnx",
                "version": "1.21.0"
            }
        ]
    },
    {
        "date": "04/07/2026 00:54:05",
        "failed": 31,
        "passed": 1796,
        "skipped": 0,
        "total_ops": 201,
        "versions": [
            {
                "name": "onnx",
                "version": "1.21.0"
            }
        ]
    }
]